libname/__init__.py
libname/calculations.py
libname/hello.py
calculations_xfms-0.0.1.dist-info/METADATA
calculations_xfms-0.0.1.dist-info/WHEEL
calculations_xfms-0.0.1.dist-info/top_level.txt
calculations_xfms-0.0.1.dist-info/RECORD
