Metadata-Version: 2.1
Name: calculations-xfms
Version: 0.0.1
Summary: Basic functions
Author: Harsha
Author-email: <harshanit400@gmail.com>
Keywords: python,calculations,add,sum,sub,mul,div
Classifier: Development Status :: 1 - Planning
Classifier: Intended Audience :: Developers
Classifier: Programming Language :: Python :: 3
Classifier: Operating System :: Unix
Classifier: Operating System :: MacOS :: MacOS X
Classifier: Operating System :: Microsoft :: Windows
